tools4rdf/__init__.py
tools4rdf/visualize.py
tools4rdf/data/cmso.owl
tools4rdf/network/__init__.py
tools4rdf/network/attrsetter.py
tools4rdf/network/network.py
tools4rdf/network/ontology.py
tools4rdf/network/parser.py
tools4rdf/network/patch.py
tools4rdf/network/term.py
tools4rdf-0.3.8.dist-info/licenses/LICENSE
tools4rdf-0.3.8.dist-info/METADATA
tools4rdf-0.3.8.dist-info/WHEEL
tools4rdf-0.3.8.dist-info/top_level.txt
tools4rdf-0.3.8.dist-info/RECORD
