Metadata-Version: 2.4
Name: tools4rdf
Version: 0.3.8
Summary: python tool for working with ontologies and data models
Author-email: Abril Azocar Guzman <sarath.menon@pyscal.org>, Sarath Menon <sarath.menon@pyscal.org>
Maintainer-email: Sarath Menon <sarath.menon@pyscal.org>
License: MIT
Project-URL: Homepage, https://pyscal.org
Project-URL: Documentation, https://pyscal.org
Project-URL: Repository, https://github.com/ocdo/tools4rdf
Project-URL: Download, https://github.com/ocdo/tools4rdf
Keywords: ontology,rdf,sparql,semantic-web,knowledge-graph
Classifier: Programming Language :: Python :: 3
Classifier: Programming Language :: Python :: 3.8
Classifier: Programming Language :: Python :: 3.9
Classifier: Programming Language :: Python :: 3.10
Classifier: Programming Language :: Python :: 3.11
Classifier: Programming Language :: Python :: 3.12
Classifier: License :: OSI Approved :: MIT License
Classifier: Operating System :: OS Independent
Classifier: Intended Audience :: Science/Research
Classifier: Topic :: Scientific/Engineering
Requires-Python: >=3.8
License-File: LICENSE
Requires-Dist: numpy
Requires-Dist: rdflib
Requires-Dist: pyyaml
Requires-Dist: graphviz
Requires-Dist: networkx
Requires-Dist: pandas
Provides-Extra: dev
Requires-Dist: pytest>=7.0; extra == "dev"
Requires-Dist: pytest-cov; extra == "dev"
Provides-Extra: docs
Requires-Dist: sphinx; extra == "docs"
Requires-Dist: sphinx-rtd-theme; extra == "docs"
Dynamic: license-file
